pollination_apps/__init__.py
pollination_apps/client.py
pollination_apps/config.py
pollination_apps/env.py
pollination_apps/login.py
pollination_apps/cli/__init__.py
pollination_apps/cli/context.py
pollination_apps/cli/assets/art.txt
pollination_apps/template/__init__.py
pollination_apps/template/dash/cookiecutter.json
pollination_apps/template/dash/hooks/post_gen_project.py
"pollination_apps/template/dash/{{cookiecutter.app_name.lower().replace(' ', '-') }}/.gitignore"
"pollination_apps/template/dash/{{cookiecutter.app_name.lower().replace(' ', '-') }}/.releaserc.json"
"pollination_apps/template/dash/{{cookiecutter.app_name.lower().replace(' ', '-') }}/README.md"
"pollination_apps/template/dash/{{cookiecutter.app_name.lower().replace(' ', '-') }}/.github/workflows/ci-automated.yaml"
"pollination_apps/template/dash/{{cookiecutter.app_name.lower().replace(' ', '-') }}/.github/workflows/ci-manual.yaml"
"pollination_apps/template/dash/{{cookiecutter.app_name.lower().replace(' ', '-') }}/app/Dockerfile"
"pollination_apps/template/dash/{{cookiecutter.app_name.lower().replace(' ', '-') }}/app/app.py"
"pollination_apps/template/dash/{{cookiecutter.app_name.lower().replace(' ', '-') }}/app/requirements.txt"
"pollination_apps/template/dash/{{cookiecutter.app_name.lower().replace(' ', '-') }}/app/vtk.Dockerfile"
"pollination_apps/template/dash/{{cookiecutter.app_name.lower().replace(' ', '-') }}/app/.pollination/config.ini"
pollination_apps/template/react/cookiecutter.json
"pollination_apps/template/react/{{cookiecutter.app_name.lower().replace(' ', '-') }}/README.md"
"pollination_apps/template/react/{{cookiecutter.app_name.lower().replace(' ', '-') }}/.github/workflows/ci-automated.yaml"
"pollination_apps/template/react/{{cookiecutter.app_name.lower().replace(' ', '-') }}/.github/workflows/ci-manual.yaml"
"pollination_apps/template/react/{{cookiecutter.app_name.lower().replace(' ', '-') }}/app/.dockerignore"
pollination_apps-0.12.1.dist-info/LICENSE
pollination_apps-0.12.1.dist-info/METADATA
pollination_apps-0.12.1.dist-info/WHEEL
pollination_apps-0.12.1.dist-info/entry_points.txt
pollination_apps-0.12.1.dist-info/top_level.txt
pollination_apps-0.12.1.dist-info/RECORD
