Metadata-Version: 2.1
Name: pollination-apps
Version: 0.12.1
Summary: A library to setup and deploy Apps to Pollination!
Home-page: https://github.com/pollination/pollination-apps
Author: Ladybug Tools
Author-email: info@ladybug.tools
License: MIT
Classifier: Programming Language :: Python :: 3.7
Classifier: Programming Language :: Python :: 3.10
Classifier: Programming Language :: Python :: Implementation :: CPython
Classifier: License :: OSI Approved :: MIT License
Classifier: Operating System :: OS Independent
License-File: LICENSE
Requires-Dist: pollination-sdk>=0.43.0
Requires-Dist: pydantic==1.8.2
Requires-Dist: PyYAML==6.0.1
Requires-Dist: jsonschema==3.2.0
Requires-Dist: click>=7.0
Requires-Dist: python-slugify==4.0.0
Requires-Dist: cookiecutter==2.1.1
